setup.py
visio2pdf.py
visio2pdf.egg-info/PKG-INFO
visio2pdf.egg-info/SOURCES.txt
visio2pdf.egg-info/dependency_links.txt
visio2pdf.egg-info/requires.txt
visio2pdf.egg-info/top_level.txt