Metadata-Version: 1.1
Name: visio2pdf
Version: 1.0.0
Summary: Convert the first shape of the first page of a Visio file to cropped PDF file.
Home-page: https://github.com/zcold/visio2pdf
Author: Shuo Li
Author-email: contact@shuo.li
License: MIT
Download-URL: https://github.com/zcold/visio2pdf/tarball/1.0.0
Keywords: Visio,PDF
Platform: win32
Classifier: Development Status :: 4 - Beta
Classifier: Topic :: Multimedia :: Graphics
Classifier: License :: OSI Approved :: MIT License
